{
  "_id": "621ea35709c81df353c4b66b",
  "+oy4zZz1OkMXLRy4PEuN6A==": "UNMCNefMUDEHBEpZHrB9Nw== euyP/zSmJQcsAIhIqKrW5g==",
  "6vp4L3z9+HvDASK3o6c5hg==": "mAhEOMOkLw+2JSVteV4ceA==",
  "A4XOgx/cGFR5kOQGy9bJqA==": "Ozhw46OL96W3r3SFwV1i+A==",
  "KFeK0C0cGmlSKVOdFl/o2g==": "GeIBDjhX1ncsVEFDriwRQA==",
  "Q1OtGudk8CkocwnHcXu87Q==": "zaKYkMDO5w+V/urFnArxbg==",
  "RVcJPbkU3tNTSMaYoiuhfQ==": "Ozhw46OL96W3r3SFwV1i+A==",
  "c+TLBzOdigVGbz1k+LBU9Q==": "wEpCSHSC1ySsIsMPABsx0w==",
  "t61idCsTdeSTSxD6+6OAUw==": "1obPf3Z2cLjw9fzT6Fra+g== JYl3/xwdWLUYBMVcynG0xA== aY8b7F75u4OOm8iclv140g== oVSdq7amAU1n+TnB927HQw== vKI/N8J0WxU+1ba/gi1bAg== V+DWAoYHOdY/26EdkrcseQ== qRsTEM3a0xxoUkOrk9llaA=="
}