{
  "_id": "621ea35709c81df353c4b697",
  "+oy4zZz1OkMXLRy4PEuN6A==": "BBNLBhkHcKtBQrnpXTthFQ== FiTSLiH6tBUYet7xSm5ekg== m3KPYd7GV5iIIpCTuCIsWQ==",
  "6vp4L3z9+HvDASK3o6c5hg==": "meMXIWMapbPbKznyp0LzYg==",
  "A4XOgx/cGFR5kOQGy9bJqA==": "Ozhw46OL96W3r3SFwV1i+A==",
  "KFeK0C0cGmlSKVOdFl/o2g==": "GeIBDjhX1ncsVEFDriwRQA==",
  "Q1OtGudk8CkocwnHcXu87Q==": "R2rxS9HukdWYBR/Lk3EBVg==",
  "RVcJPbkU3tNTSMaYoiuhfQ==": "Ozhw46OL96W3r3SFwV1i+A==",
  "c+TLBzOdigVGbz1k+LBU9Q==": "xhD2absdxXN7L8JiuYwBpA==",
  "t61idCsTdeSTSxD6+6OAUw==": "hk3bYm16E9GEh9cqeJGSEg== JoHvRQGqAiMToeh+/mUp3Q== HulD4I1fZPidMQyBlC3iSg== NjDm1Cvrb0997crKiRl/aQ== UXQbdM/byTy1atF6smExIA== y5u1nb1Qf8Tx2KutIo3eMA== er4vv93V/gEhw99d+zDiEg== oL9Rz8bnmJvvVKpJDdN3wA== llsLNT7O0q3Z6ePuCx3V6w== WwvJk6upOC08Cwt9PHjkxg== +ED9q6wVPJr87kGnfH7/vg== 9FoilBFEV8XmjOfiEyefng== zNruNunnM7ZIQnBWYWS19g== gJPYQXXTSOccJ5i1W0VhcA== gewujXcUZkDikL4A3Q3TQw=="
}