{
  "_id": "621ea35709c81df353c4b926",
  "+oy4zZz1OkMXLRy4PEuN6A==": "tLgtCC+LIrHpNPWS8JjHaw== yq1bkqana1cRU7991ziwsQ== m3KPYd7GV5iIIpCTuCIsWQ==",
  "6vp4L3z9+HvDASK3o6c5hg==": "s/wWONmaMjCUtFEEOkW6Dg==",
  "A4XOgx/cGFR5kOQGy9bJqA==": "Ozhw46OL96W3r3SFwV1i+A==",
  "KFeK0C0cGmlSKVOdFl/o2g==": "GeIBDjhX1ncsVEFDriwRQA==",
  "Q1OtGudk8CkocwnHcXu87Q==": "1Df+lKB/YRzzoo8ah+3+JA==",
  "RVcJPbkU3tNTSMaYoiuhfQ==": "Ozhw46OL96W3r3SFwV1i+A==",
  "c+TLBzOdigVGbz1k+LBU9Q==": "lCBnRsZHDN3afu9mDMcyeQ==",
  "t61idCsTdeSTSxD6+6OAUw==": "UHFTxD2xu4AyXVBX2Kuyyg== XWxHC7fOebBQqinHKQggCg== qFZAPlmXo3eTuA9Qb5Imkg== LDN+4VWnEH8FWX3K1OcNIg== HUbyhgOZcKO9zpoxfshaOA== bRJFQK3aYChOReesLuP8xg== dBL/ts5ruft0v1fHJei1cA== sjeZd+hkbZ2Rppq5dBsXgw== xo677mvqZXaB4GT7iq9zBQ== gewujXcUZkDikL4A3Q3TQw=="
}