{
  "_id": "621ea35709c81df353c4b2fa",
  "+oy4zZz1OkMXLRy4PEuN6A==": "ZpYCwWvpMNL+W7JnkkKRXQ== m3KPYd7GV5iIIpCTuCIsWQ==",
  "6vp4L3z9+HvDASK3o6c5hg==": "xCEbWXmuY6QYKoE1Vs1Gkw==",
  "A4XOgx/cGFR5kOQGy9bJqA==": "Ozhw46OL96W3r3SFwV1i+A==",
  "KFeK0C0cGmlSKVOdFl/o2g==": "GeIBDjhX1ncsVEFDriwRQA==",
  "Q1OtGudk8CkocwnHcXu87Q==": "Bow24w5PSMDaqEQf4jrFOw==",
  "RVcJPbkU3tNTSMaYoiuhfQ==": "Ozhw46OL96W3r3SFwV1i+A==",
  "c+TLBzOdigVGbz1k+LBU9Q==": "DwLEOc9LbBjEOH+5jkcumQ== A+20fE4KeHb7K+Qamqv19Q==",
  "t61idCsTdeSTSxD6+6OAUw==": "7/afXPeDua+qaRhDLy+7aQ== yRWmZbYNQdwOjupp8SaCgg== APmrlfxYp4JwlqYnwat5ig== hk3bYm16E9GEh9cqeJGSEg== JoHvRQGqAiMToeh+/mUp3Q== CHZ2r5MEyGOFAQqnVbfHZA== YrMap9g8ipEA7JZt7JA9BA== llsLNT7O0q3Z6ePuCx3V6w== Z4rMhu0M5hOHYDbmsERKaA== WK6JXDNIkDz70X+Wnp2/gw== 9FoilBFEV8XmjOfiEyefng== TAnJW7F5PrV7ZbHj0RWNpA== z5aYp2+hCrcTaW0SleI5fA== Z4rMhu0M5hOHYDbmsERKaA== 59m4Mmsf3Rwmdnd7aBdbBQ=="
}