{
  "_id": "621ea35709c81df353c4b8c2",
  "+oy4zZz1OkMXLRy4PEuN6A==": "AckQFu1AFgY5fV6yKpaxXQ== zgSsY1ZDD4qXZet6paz+eA== m3KPYd7GV5iIIpCTuCIsWQ==",
  "6vp4L3z9+HvDASK3o6c5hg==": "yQHubcHbe4KlQ2/F+JSDlw==",
  "A4XOgx/cGFR5kOQGy9bJqA==": "Ozhw46OL96W3r3SFwV1i+A==",
  "KFeK0C0cGmlSKVOdFl/o2g==": "GeIBDjhX1ncsVEFDriwRQA==",
  "Q1OtGudk8CkocwnHcXu87Q==": "DtcR+VJp2JVGTy2jps/0tg==",
  "RVcJPbkU3tNTSMaYoiuhfQ==": "Ozhw46OL96W3r3SFwV1i+A==",
  "c+TLBzOdigVGbz1k+LBU9Q==": "4pj+d3DHEFFoZODxm7rgAQ==",
  "t61idCsTdeSTSxD6+6OAUw==": "BWarhNdJOPEnMaVb9kcuOQ== 89nmfklLDgDVrTGxHQ7Xtg== j61lXrxNFBundw4F2hRrtw== JOeR/BRuA/jcyTb2tt1PvA== UXQbdM/byTy1atF6smExIA== 0ObKDW4BRHGgUjUV659FYA== BWarhNdJOPEnMaVb9kcuOQ== Dj23kfqOZqzufWBflx7+TQ=="
}