{
  "_id": "621ea35709c81df353c4b73c",
  "+oy4zZz1OkMXLRy4PEuN6A==": "hfoI2XymZSW1lQzDq37LmA== j8TMcBW2GRSNh5m+Fluxhg==",
  "6vp4L3z9+HvDASK3o6c5hg==": "7NsB2wWjYVZzoH2wJgEzQQ==",
  "A4XOgx/cGFR5kOQGy9bJqA==": "Ozhw46OL96W3r3SFwV1i+A==",
  "KFeK0C0cGmlSKVOdFl/o2g==": "GeIBDjhX1ncsVEFDriwRQA==",
  "Q1OtGudk8CkocwnHcXu87Q==": "ufORREdA3d5dr3TLIj4NlA==",
  "RVcJPbkU3tNTSMaYoiuhfQ==": "Ozhw46OL96W3r3SFwV1i+A==",
  "c+TLBzOdigVGbz1k+LBU9Q==": "wEpCSHSC1ySsIsMPABsx0w==",
  "t61idCsTdeSTSxD6+6OAUw==": "lHiGP2aupsYFXLPIHY0JsA== tJJjkIFJ2YGb9x8a6TdxxQ== 3lI4/KoatVxtZETNtgNNmw== wZ9r0CTyO3TwxllxiJG/wA== 3q1o12Nz3DPQc8sMzgl3IA== c6a6mwKAyfNfp85Jy2do8A== 4zc3T5Gph8OPWZ8s3SKCsA== 8wxQ5kA7zLbZppkvXPMYdQ== lEFAqhsuKWjXkjYHY+iM8w== Si/PgaTFwNh9PwGKnOUOjQ== /k+tF1p6FY9/RDTR/h3OJQ== qRsTEM3a0xxoUkOrk9llaA=="
}