{
  "_id": "621ea35709c81df353c4b2cd",
  "+oy4zZz1OkMXLRy4PEuN6A==": "hA+keUDT7OKQC4XNHuor1w== x4E2o8hBUG0Tbl7QcqKajA==",
  "6vp4L3z9+HvDASK3o6c5hg==": "7IL/wPFfNA+tYA56CS2ZLg==",
  "A4XOgx/cGFR5kOQGy9bJqA==": "Ozhw46OL96W3r3SFwV1i+A==",
  "KFeK0C0cGmlSKVOdFl/o2g==": "GeIBDjhX1ncsVEFDriwRQA==",
  "Q1OtGudk8CkocwnHcXu87Q==": "xhpaDvSx7Mva2TRaq63nWw==",
  "RVcJPbkU3tNTSMaYoiuhfQ==": "Ozhw46OL96W3r3SFwV1i+A==",
  "c+TLBzOdigVGbz1k+LBU9Q==": "eKNRubfDFR+iqXc4BiF2cw==",
  "t61idCsTdeSTSxD6+6OAUw==": "T0N8FXcHVKjCT8P+8gfkSQ== m124KkaRyZ6JN0oojoKQbg== GPiZaiVxJFNjlAqCyJw5Rg== uidtQuj3XrPRNtvzvDXpMg== wuCdPx76dVr8p5+5nKgrbQ== XWxHC7fOebBQqinHKQggCg== 4bJims/9+jJBijjPCYQ7Dg== wx+1mG5RPkrvJZaZl9QFvA== CVv0jEM6jtjDQTwYo6pXBQ== llsLNT7O0q3Z6ePuCx3V6w== hxEbihMSK3zMTZPrXy2fbg== vyZVBxdDGgCftc1/xf8hXw== TuUNHMnWwiioHiSCGV6TjA=="
}