{
  "_id": "621ea35709c81df353c4b8cb",
  "+oy4zZz1OkMXLRy4PEuN6A==": "wyD0YfpqUGSZVT9n9m1rxg== oyXYv24W/7WWmd7zqhU3WA== DPNlu8zsJs45NVBo/GUw0w== m3KPYd7GV5iIIpCTuCIsWQ==",
  "6vp4L3z9+HvDASK3o6c5hg==": "CFsvbUn0ulumw2/MaZeNqg==",
  "A4XOgx/cGFR5kOQGy9bJqA==": "Ozhw46OL96W3r3SFwV1i+A==",
  "KFeK0C0cGmlSKVOdFl/o2g==": "GeIBDjhX1ncsVEFDriwRQA==",
  "Q1OtGudk8CkocwnHcXu87Q==": "it5GC4E/4oz0phHKijjR1w==",
  "RVcJPbkU3tNTSMaYoiuhfQ==": "Ozhw46OL96W3r3SFwV1i+A==",
  "c+TLBzOdigVGbz1k+LBU9Q==": "GeIBDjhX1ncsVEFDriwRQA==",
  "t61idCsTdeSTSxD6+6OAUw==": "mQUuvtzyyRP43t8hOJHcqQ== C7FeQvuUGye9dlV226lwAQ== AxssDrdZ3nmdAnmFb6H/sg== aR0MZdspLpIRcOU2EHwogA== XQOrPEcyrKn/4mKLXv5ckQ== z5aYp2+hCrcTaW0SleI5fA== KTXqghE7K6Eankq6qvf8Lw=="
}