{
  "_id": "621ea35709c81df353c4b651",
  "+oy4zZz1OkMXLRy4PEuN6A==": "x5OgO5HL6M04GVXfnp7X6w== m3KPYd7GV5iIIpCTuCIsWQ==",
  "6vp4L3z9+HvDASK3o6c5hg==": "CmZZYITfML18M4aIn3pytA==",
  "A4XOgx/cGFR5kOQGy9bJqA==": "Ozhw46OL96W3r3SFwV1i+A==",
  "KFeK0C0cGmlSKVOdFl/o2g==": "GeIBDjhX1ncsVEFDriwRQA==",
  "Q1OtGudk8CkocwnHcXu87Q==": "Sw1L4cUZexJPhnHSYNZDvQ==",
  "RVcJPbkU3tNTSMaYoiuhfQ==": "Ozhw46OL96W3r3SFwV1i+A==",
  "c+TLBzOdigVGbz1k+LBU9Q==": "mz8G2QEH2vDFDtmbbv37kQ==",
  "t61idCsTdeSTSxD6+6OAUw==": "Bi/ESqZsgw/TCFtY3LbWSA== 89nmfklLDgDVrTGxHQ7Xtg== 8GpP3kRanER5uMawaMUj8Q== 7/afXPeDua+qaRhDLy+7aQ== AqnRv+v2GSWOtzAEx55eZA== 7xfcm+ZSef4iCtFTtox5ig== ZIx7Q7emIjoB1waK2LxNLQ== uIGfRMCP/7admszsbMiHmw== ZKMllfRavsex2hP33G4R6g== VFonNb9iMmNj8NUU63F3Fw=="
}