{
  "_id": "621ea35709c81df353c4b7c4",
  "+oy4zZz1OkMXLRy4PEuN6A==": "uIGfRMCP/7admszsbMiHmw== us3PPAG2AwcCUFqhhKZD6A==",
  "6vp4L3z9+HvDASK3o6c5hg==": "DNs0wvmH9rwj0HfNNPp3ig==",
  "A4XOgx/cGFR5kOQGy9bJqA==": "Ozhw46OL96W3r3SFwV1i+A==",
  "KFeK0C0cGmlSKVOdFl/o2g==": "GeIBDjhX1ncsVEFDriwRQA==",
  "Q1OtGudk8CkocwnHcXu87Q==": "kUVHaOmxQrFu4OCLH0wzWw==",
  "RVcJPbkU3tNTSMaYoiuhfQ==": "Ozhw46OL96W3r3SFwV1i+A==",
  "c+TLBzOdigVGbz1k+LBU9Q==": "SVDiS6T1aK1jUAtuDNt4eg==",
  "t61idCsTdeSTSxD6+6OAUw==": "thrRWkzb4QCnkB4Kz6DOJw== YCyN5/KpSFNidRSjBJpc4g== sXbVxreojcPWZwWfY+cr6A== s7xfouprDy5twX3bDp71WA=="
}