{
  "_id": "621ea35709c81df353c4b35d",
  "+oy4zZz1OkMXLRy4PEuN6A==": "5Uk54nYCe/nR7PMZab/dWg== i85qu6jSm5id06Cq9BtCcg==",
  "6vp4L3z9+HvDASK3o6c5hg==": "L3/YZcM96+J7Sa8N3trRiA==",
  "A4XOgx/cGFR5kOQGy9bJqA==": "Ozhw46OL96W3r3SFwV1i+A==",
  "KFeK0C0cGmlSKVOdFl/o2g==": "GeIBDjhX1ncsVEFDriwRQA==",
  "Q1OtGudk8CkocwnHcXu87Q==": "8pQPrLOWDItDDzvXtSSd2w==",
  "RVcJPbkU3tNTSMaYoiuhfQ==": "Ozhw46OL96W3r3SFwV1i+A==",
  "c+TLBzOdigVGbz1k+LBU9Q==": "WEsWZtIrf3LG3IaVBjgMsg==",
  "t61idCsTdeSTSxD6+6OAUw==": "Yj7LcE2x7tfQFAel1WAHNg== yQfNHsRcvo6zQtqZyh0e6g== xIed29DflYeHpQE4BiLrxA== 3oWR/T/bhvxru22d6sUrRQ== LO+VR7JnQEx5s/i7QuVRAg== sdpaCuyOLTNzl0wPCrE8Jg== E6F5AmX7amqJLa4WezQISA== z5aYp2+hCrcTaW0SleI5fA== 7QxA/tetLn2ZJq1DJg1D/w=="
}