{
  "_id": "621ea35709c81df353c4b7ca",
  "+oy4zZz1OkMXLRy4PEuN6A==": "Ym5OfBoznX0WpbrITMJqUw== hfoI2XymZSW1lQzDq37LmA==",
  "6vp4L3z9+HvDASK3o6c5hg==": "TBDpS+6TwN/3RryK3wQR9w==",
  "A4XOgx/cGFR5kOQGy9bJqA==": "Ozhw46OL96W3r3SFwV1i+A==",
  "KFeK0C0cGmlSKVOdFl/o2g==": "GeIBDjhX1ncsVEFDriwRQA==",
  "Q1OtGudk8CkocwnHcXu87Q==": "C2zWV2WTE+TAiT9tic6VyA==",
  "RVcJPbkU3tNTSMaYoiuhfQ==": "Ozhw46OL96W3r3SFwV1i+A==",
  "c+TLBzOdigVGbz1k+LBU9Q==": "wEpCSHSC1ySsIsMPABsx0w==",
  "t61idCsTdeSTSxD6+6OAUw==": "CdyDc4nZ0p2UGz7mC+o+DA== EWJ8iocgWeqiIyXyULM89A== zkJbPjdGQ3kCVhhLRrgPng== 9fLjqOaJIti6PnQmU6AbCw== XWxHC7fOebBQqinHKQggCg== AQ8q3fmIKQVFHM8VdOukKg== aKVNZzSzPF5TIfxxYSqw7g== WgFdCxAYQzTSjw069PtEHw== XWxHC7fOebBQqinHKQggCg== CdyDc4nZ0p2UGz7mC+o+DA== CdyDc4nZ0p2UGz7mC+o+DA== qRsTEM3a0xxoUkOrk9llaA=="
}