{
  "_id": "621ea35709c81df353c4b5f9",
  "+oy4zZz1OkMXLRy4PEuN6A==": "cMzN26tALLVfv2Szv/MM4Q== I2qENGUvzvZ65zdDfee3Ng== m3KPYd7GV5iIIpCTuCIsWQ==",
  "6vp4L3z9+HvDASK3o6c5hg==": "Tt8WpTL1zadMyGGYwtzLNA==",
  "A4XOgx/cGFR5kOQGy9bJqA==": "Ozhw46OL96W3r3SFwV1i+A==",
  "KFeK0C0cGmlSKVOdFl/o2g==": "GeIBDjhX1ncsVEFDriwRQA==",
  "Q1OtGudk8CkocwnHcXu87Q==": "PLwriHyGrbqsVhZrpkBVWw==",
  "RVcJPbkU3tNTSMaYoiuhfQ==": "Ozhw46OL96W3r3SFwV1i+A==",
  "c+TLBzOdigVGbz1k+LBU9Q==": "OCnCy4OGsLgAodXpbMNEHQ==",
  "t61idCsTdeSTSxD6+6OAUw==": "TgSr/XbMBxUU5I0OSrhrmA== 0cwQT8P0twRRSpg5WUdZ2g== CWA4MEoEwXJr/frjuTfEqw== 0UABGTFJGsyv5u2d+NXC7w== hrzyoerPOEUuiSKVdC1EqQ== 6WJNKyyzgbyYVRL1HKwKzA== 8wxQ5kA7zLbZppkvXPMYdQ== 4RVewsNzkZ9yQYR59uC/bQ== qV1i16kKnCiFS2diim+Q4w== JnMEaVHY+x3wCw0L1/mEhg== z5aYp2+hCrcTaW0SleI5fA== 66e7sQ/3fvW1+ox8B/+M1Q=="
}