{
  "_id": "621ea35709c81df353c4b49a",
  "+oy4zZz1OkMXLRy4PEuN6A==": "ybvkHpvWU5tsGTOpsEUmFQ== rfbEAQ+rHAUkMIIoidCbyg== rfbEAQ+rHAUkMIIoidCbyg== m3KPYd7GV5iIIpCTuCIsWQ==",
  "6vp4L3z9+HvDASK3o6c5hg==": "UDn3TDW5XL/dytNwPuoEBQ==",
  "A4XOgx/cGFR5kOQGy9bJqA==": "Ozhw46OL96W3r3SFwV1i+A==",
  "KFeK0C0cGmlSKVOdFl/o2g==": "GeIBDjhX1ncsVEFDriwRQA==",
  "Q1OtGudk8CkocwnHcXu87Q==": "Q+44fI1bTD2yIzs1hU/5ig==",
  "RVcJPbkU3tNTSMaYoiuhfQ==": "Ozhw46OL96W3r3SFwV1i+A==",
  "c+TLBzOdigVGbz1k+LBU9Q==": "SVDiS6T1aK1jUAtuDNt4eg==",
  "t61idCsTdeSTSxD6+6OAUw==": "hk3bYm16E9GEh9cqeJGSEg== JoHvRQGqAiMToeh+/mUp3Q== uVTVM7PUrnvFUFZfohOQDw== NjDm1Cvrb0997crKiRl/aQ== UXQbdM/byTy1atF6smExIA== 5/6kHRb/BiU1R95RYlVdcA== sjeZd+hkbZ2Rppq5dBsXgw== er4vv93V/gEhw99d+zDiEg== llsLNT7O0q3Z6ePuCx3V6w== uVTVM7PUrnvFUFZfohOQDw== 9FoilBFEV8XmjOfiEyefng== uVTVM7PUrnvFUFZfohOQDw== gewujXcUZkDikL4A3Q3TQw=="
}