{
  "_id": "621ea35709c81df353c4b404",
  "+oy4zZz1OkMXLRy4PEuN6A==": "OeYup+pwm112id8UnBHGFw== m3KPYd7GV5iIIpCTuCIsWQ==",
  "6vp4L3z9+HvDASK3o6c5hg==": "W+LQjUWnDNwUWdc1hPP6Cg==",
  "A4XOgx/cGFR5kOQGy9bJqA==": "Ozhw46OL96W3r3SFwV1i+A==",
  "KFeK0C0cGmlSKVOdFl/o2g==": "GeIBDjhX1ncsVEFDriwRQA==",
  "Q1OtGudk8CkocwnHcXu87Q==": "kP/UCyfA52qBbs1fDIxL4w==",
  "RVcJPbkU3tNTSMaYoiuhfQ==": "Ozhw46OL96W3r3SFwV1i+A==",
  "c+TLBzOdigVGbz1k+LBU9Q==": "GeIBDjhX1ncsVEFDriwRQA==",
  "t61idCsTdeSTSxD6+6OAUw==": "J8D1JOabIHs1xxumO79U0A== UXQbdM/byTy1atF6smExIA== 8UwilXuma7Vq6b5Qw3v6iQ== 2Yp68jb2z0EorR3MUNcbYQ== UXQbdM/byTy1atF6smExIA== rFLsKes3diTUYrQitb/6Xw== AUvO0nwZn03ShJfbdYN9qQ== 1XIWrUE4oA68fCiloQd80A== pODDWMP4+q93sfbAC/2nrg== XQ5rOAYcRBdZ7YQMx9Me1w== j79LIYe5nDjXPhV3cRXGOg== 9FoilBFEV8XmjOfiEyefng== gks1T5GH/h+rBPepSX0YmA== CheJjF5SnHG75J4+px9uVg=="
}