{
  "_id": "621ea35709c81df353c4b2c1",
  "+oy4zZz1OkMXLRy4PEuN6A==": "Y0nstw3yv0QtUIF1eJfUyg== wZ9r0CTyO3TwxllxiJG/wA== m3KPYd7GV5iIIpCTuCIsWQ==",
  "6vp4L3z9+HvDASK3o6c5hg==": "YrJYZpKUJcq+si1nKfFSPQ==",
  "A4XOgx/cGFR5kOQGy9bJqA==": "Ozhw46OL96W3r3SFwV1i+A==",
  "KFeK0C0cGmlSKVOdFl/o2g==": "GeIBDjhX1ncsVEFDriwRQA==",
  "Q1OtGudk8CkocwnHcXu87Q==": "WXgb8jwbRj83enDH4TkYPQ==",
  "RVcJPbkU3tNTSMaYoiuhfQ==": "Ozhw46OL96W3r3SFwV1i+A==",
  "c+TLBzOdigVGbz1k+LBU9Q==": "z6XYEbLlUgDjZgKk9QWtVQ==",
  "t61idCsTdeSTSxD6+6OAUw==": "YRp0X+kJbHDuCBW/clgfzA== LaqAWGagFfn/I+kxnSk7Fw== 7SVDpVd0rM91wHiBFGMeQA== LHFz+Xw4PhubEywV4aJSqQ== +ED9q6wVPJr87kGnfH7/vg== z5aYp2+hCrcTaW0SleI5fA== ky+VjSLJqqFaaA6N2TuGJw==",
  "wzLSOh3rlJ1X16gfkdyKGQ==": "sBfzZ+M0UQMiLVbzKJv63A=="
}