{
  "_id": "621ea35709c81df353c4b38f",
  "+oy4zZz1OkMXLRy4PEuN6A==": "uIGfRMCP/7admszsbMiHmw== G24wyXNIqslcnv8DFof4lw==",
  "6vp4L3z9+HvDASK3o6c5hg==": "bjgEOjk2xn4KgkK9HJfsiQ==",
  "A4XOgx/cGFR5kOQGy9bJqA==": "Ozhw46OL96W3r3SFwV1i+A==",
  "KFeK0C0cGmlSKVOdFl/o2g==": "GeIBDjhX1ncsVEFDriwRQA==",
  "Q1OtGudk8CkocwnHcXu87Q==": "EzM6PpZypEuskGDHNkIFwQ==",
  "RVcJPbkU3tNTSMaYoiuhfQ==": "Ozhw46OL96W3r3SFwV1i+A==",
  "c+TLBzOdigVGbz1k+LBU9Q==": "z1iJQQJAtOKuUD3L4qYIDA==",
  "t61idCsTdeSTSxD6+6OAUw==": "9rDaBTQcAhDUj8bGvKakxg== 9aoKohkb2YvXb0mMp502xg== lx05dT/9joKVGsCe1Pvmww== vyZVBxdDGgCftc1/xf8hXw== 31wS/Dr7GoGCas48VrhN+w== z5aYp2+hCrcTaW0SleI5fA== 3DvHndvS76v8ruYM8+OdzQ=="
}